NiukeFpgaGongchengshiQiuzhiJingyanFenxiang20212022/README.md
NiukeFpgaGongchengshiQiuzhiJingyanFenxiang20212022/__init__.py
NiukeFpgaGongchengshiQiuzhiJingyanFenxiang20212022/__main__.py
NiukeFpgaGongchengshiQiuzhiJingyanFenxiang20212022/file.epub
NiukeFpgaGongchengshiQiuzhiJingyanFenxiang20212022/index.html
NiukeFpgaGongchengshiQiuzhiJingyanFenxiang20212022/css/__init__.py
NiukeFpgaGongchengshiQiuzhiJingyanFenxiang20212022/css/annotations.css
NiukeFpgaGongchengshiQiuzhiJingyanFenxiang20212022/css/main.css
NiukeFpgaGongchengshiQiuzhiJingyanFenxiang20212022/css/normalize.css
NiukeFpgaGongchengshiQiuzhiJingyanFenxiang20212022/css/popup.css
NiukeFpgaGongchengshiQiuzhiJingyanFenxiang20212022/font/__init__.py
NiukeFpgaGongchengshiQiuzhiJingyanFenxiang20212022/font/fontello.eot
NiukeFpgaGongchengshiQiuzhiJingyanFenxiang20212022/font/fontello.svg
NiukeFpgaGongchengshiQiuzhiJingyanFenxiang20212022/font/fontello.ttf
NiukeFpgaGongchengshiQiuzhiJingyanFenxiang20212022/font/fontello.woff
NiukeFpgaGongchengshiQiuzhiJingyanFenxiang20212022/img/__init__.py
NiukeFpgaGongchengshiQiuzhiJingyanFenxiang20212022/img/annotator-glyph-sprite.png
NiukeFpgaGongchengshiQiuzhiJingyanFenxiang20212022/img/annotator-icon-sprite.png
NiukeFpgaGongchengshiQiuzhiJingyanFenxiang20212022/img/apple-touch-icon.png
NiukeFpgaGongchengshiQiuzhiJingyanFenxiang20212022/img/cancelfullscreen.png
NiukeFpgaGongchengshiQiuzhiJingyanFenxiang20212022/img/close.png
NiukeFpgaGongchengshiQiuzhiJingyanFenxiang20212022/img/fullscreen.png
NiukeFpgaGongchengshiQiuzhiJingyanFenxiang20212022/img/loader.gif
NiukeFpgaGongchengshiQiuzhiJingyanFenxiang20212022/img/menu-icon.png
NiukeFpgaGongchengshiQiuzhiJingyanFenxiang20212022/img/save.png
NiukeFpgaGongchengshiQiuzhiJingyanFenxiang20212022/img/saved.png
NiukeFpgaGongchengshiQiuzhiJingyanFenxiang20212022/img/settings-s.png
NiukeFpgaGongchengshiQiuzhiJingyanFenxiang20212022/img/settings.png
NiukeFpgaGongchengshiQiuzhiJingyanFenxiang20212022/img/star.png
niuke_fpga_gongchengshi_qiuzhi_jingyan_fenxiang_2021_2022-2024.3.6.0.dist-info/METADATA
niuke_fpga_gongchengshi_qiuzhi_jingyan_fenxiang_2021_2022-2024.3.6.0.dist-info/WHEEL
niuke_fpga_gongchengshi_qiuzhi_jingyan_fenxiang_2021_2022-2024.3.6.0.dist-info/entry_points.txt
niuke_fpga_gongchengshi_qiuzhi_jingyan_fenxiang_2021_2022-2024.3.6.0.dist-info/top_level.txt
niuke_fpga_gongchengshi_qiuzhi_jingyan_fenxiang_2021_2022-2024.3.6.0.dist-info/RECORD
